LICENSE
MANIFEST.in
README.md
obspycsv.py
setup.py
test_obspycsv.py
obspycsv.egg-info/PKG-INFO
obspycsv.egg-info/SOURCES.txt
obspycsv.egg-info/dependency_links.txt
obspycsv.egg-info/entry_points.txt
obspycsv.egg-info/not-zip-safe
obspycsv.egg-info/requires.txt
obspycsv.egg-info/top_level.txt